src/__init__.py
src/dbscan.py
src/kmeans.py
src/utils.py
IlliaN.clustering-0.0.1.dist-info/METADATA
IlliaN.clustering-0.0.1.dist-info/WHEEL
IlliaN.clustering-0.0.1.dist-info/top_level.txt
IlliaN.clustering-0.0.1.dist-info/RECORD
